seavoyage/__init__.py
seavoyage/base.py
seavoyage/constants.py
seavoyage/exceptions.py
seavoyage/log.py
seavoyage/settings.py
seavoyage/classes/__init__.py
seavoyage/classes/m_network.py
seavoyage/data/geojson/marnet/10km_modified.geojson
seavoyage/data/geojson/marnet/edge_sample.geojson
seavoyage/data/geojson/marnet/marnet_plus_100km.geojson
seavoyage/data/geojson/marnet/marnet_plus_10km.geojson
seavoyage/data/geojson/marnet/marnet_plus_20km.geojson
seavoyage/data/geojson/marnet/marnet_plus_50km.geojson
seavoyage/data/geojson/marnet/marnet_plus_5km.geojson
seavoyage/data/ports/WPI150.csv
seavoyage/data/samples/additional_points.geojson
seavoyage/data/samples/cross_land.geojson
seavoyage/data/samples/hires_nodes.geojson
seavoyage/data/shorelines/README.TXT
seavoyage/data/shorelines/c/GSHHS_c_L1.dbf
seavoyage/data/shorelines/c/GSHHS_c_L1.prj
seavoyage/data/shorelines/c/GSHHS_c_L1.shp
seavoyage/data/shorelines/c/GSHHS_c_L1.shx
seavoyage/data/shorelines/h/GSHHS_h_L1.dbf
seavoyage/data/shorelines/h/GSHHS_h_L1.prj
seavoyage/data/shorelines/h/GSHHS_h_L1.shp
seavoyage/data/shorelines/h/GSHHS_h_L1.shx
seavoyage/data/shorelines/i/GSHHS_i_L1.dbf
seavoyage/data/shorelines/i/GSHHS_i_L1.prj
seavoyage/data/shorelines/i/GSHHS_i_L1.shp
seavoyage/data/shorelines/i/GSHHS_i_L1.shx
seavoyage/data/shorelines/l/GSHHS_l_L1.dbf
seavoyage/data/shorelines/l/GSHHS_l_L1.prj
seavoyage/data/shorelines/l/GSHHS_l_L1.shp
seavoyage/data/shorelines/l/GSHHS_l_L1.shx
seavoyage/modules/__init__.py
seavoyage/modules/restriction.py
seavoyage/tests/test_restrictions_reset.py
seavoyage/utils/__init__.py
seavoyage/utils/coordinates.py
seavoyage/utils/geojson_utils.py
seavoyage/utils/map_utils.py
seavoyage/utils/marine_network.py
seavoyage/utils/route_utils.py
seavoyage/utils/shapely_utils.py
seavoyage/utils/shoreline.py
seavoyage-0.1.20.dist-info/licenses/LICENSE
seavoyage-0.1.20.dist-info/METADATA
seavoyage-0.1.20.dist-info/WHEEL
seavoyage-0.1.20.dist-info/top_level.txt
seavoyage-0.1.20.dist-info/RECORD
