Metadata-Version: 2.4
Name: seavoyage
Version: 0.1.20
Summary: An improved version of searoute package for calculating the shortest sea route between two points on Earth.
Author-email: Byeonggong Hwang <bk22106@gmail.com>
License: Apache 2.0
Project-URL: Homepage, https://github.com/a22106/seavoyage
Keywords: sea route,shortest path,graph,geojson,networkx
Classifier: Development Status :: 4 - Beta
Classifier: Intended Audience :: Developers
Classifier: Intended Audience :: Science/Research
Classifier: License :: OSI Approved :: Apache Software License
Classifier: Operating System :: OS Independent
Classifier: Programming Language :: Python
Classifier: Programming Language :: Python :: 3
Classifier: Programming Language :: Python :: 3.9
Classifier: Programming Language :: Python :: 3.10
Classifier: Programming Language :: Python :: 3.11
Classifier: Programming Language :: Python :: 3.12
Classifier: Programming Language :: Python :: 3.13
Classifier: Topic :: Scientific/Engineering :: GIS
Requires-Python: >=3.11
License-File: LICENSE
Requires-Dist: folium>=0.19.5
Requires-Dist: geojson>=3.2.0
Requires-Dist: geopandas>=1.0.1
Requires-Dist: haversine>=2.9.0
Requires-Dist: myst-parser>=4.0.0
Requires-Dist: networkx>=3.4.2
Requires-Dist: pytest>=8.3.5
Requires-Dist: ruff>=0.11.7
Requires-Dist: scikit-learn>=1.6.1
Requires-Dist: scipy>=1.13.0
Requires-Dist: searoute>=1.4.3
Requires-Dist: shapely>=2.1.0
Requires-Dist: sphinx-rtd-theme>=3.0.2
Dynamic: license-file
